dbreak/__init__.py
dbreak/commands.py
dbreak/connections.py
dbreak/console.py
dbreak/constants.py
dbreak/dbapi.py
dbreak/exc.py
dbreak/outputs.py
dbreak/parser.py
dbreak/sessions.py
dbreak-0.0.1.dist-info/LICENSE
dbreak-0.0.1.dist-info/METADATA
dbreak-0.0.1.dist-info/WHEEL
dbreak-0.0.1.dist-info/entry_points.txt
dbreak-0.0.1.dist-info/top_level.txt
dbreak-0.0.1.dist-info/RECORD
