Metadata-Version: 2.1
Name: dbreak
Version: 0.0.1
Summary: Console for live debugging of development databases
Home-page: https://github.com/jrhege/dbreak
Author: Johnathon Hege
License: UNKNOWN
Keywords: development database
Platform: UNKNOWN
Classifier: Development Status :: 3 - Alpha
Classifier: Intended Audience :: Developers
Classifier: License :: OSI Approved :: MIT License
Classifier: Programming Language :: Python :: 3.6
Classifier: Programming Language :: Python :: 3.7
Classifier: Programming Language :: Python :: 3.8
Requires-Python: >=3.6
Requires-Dist: tabulate (>=0.8.6)
